pydft/__init__.py
pydft/_version.py
pydft/angulargrid.py
pydft/atomicgrid.py
pydft/bragg_slater.py
pydft/dft.py
pydft/moleculargrid.py
pydft/spherical_harmonics.py
pydft/xcfunctionals.py
pydft-0.7.4.dist-info/METADATA
pydft-0.7.4.dist-info/WHEEL
pydft-0.7.4.dist-info/top_level.txt
pydft-0.7.4.dist-info/RECORD
