Metadata-Version: 2.4
Name: pydft
Version: 0.7.4
Summary: pydft
Home-page: https://github.com/ifilot/pydft
Author: Ivo Filot
Author-email: Ivo Filot <ivo@ivofilot.nl>
Maintainer-email: Ivo Filot <ivo@ivofilot.nl>
License: GPL-3.0-or-later
Project-URL: Homepage, https://github.com/ifilot/pydft
Project-URL: Bug Tracker, https://github.com/ifilot/pydft/issues
Classifier: Programming Language :: Python :: 3
Classifier: Operating System :: OS Independent
Requires-Python: >=3.5
Requires-Dist: scipy>=1.15
Requires-Dist: numpy
Requires-Dist: pyqint
Requires-Dist: pylebedev
Dynamic: author
Dynamic: home-page
Dynamic: requires-python
